MANIFEST.in
README.rst
requirements.txt
setup.py
ps_crud/__init__.py
ps_crud.egg-info/PKG-INFO
ps_crud.egg-info/SOURCES.txt
ps_crud.egg-info/dependency_links.txt
ps_crud.egg-info/not-zip-safe
ps_crud.egg-info/requires.txt
ps_crud.egg-info/top_level.txt
ps_crud/static/ps_crud/js/assets/__main.js
ps_crud/static/ps_crud/js/assets/__main.js.map
ps_crud/static/ps_crud/js/src/listView.js
ps_crud/static/ps_crud/js/src/main.js
ps_crud/static/ps_crud/js/src/materialize.js
ps_crud/static/ps_crud/js/src/settings.js
ps_crud/templates/ps_crud/list.jinja2
ps_crud/templates/ps_crud/paginator.jinja2